confyml/__init__.py
confyml/confyml.py
tests/__init__.py
tests/example.py
tests/test_confyml.py
tests/resources/__init__.py
tests/resources/sample_module.py
confyml-2.1.5.dist-info/LICENSE
confyml-2.1.5.dist-info/METADATA
confyml-2.1.5.dist-info/WHEEL
confyml-2.1.5.dist-info/top_level.txt
confyml-2.1.5.dist-info/RECORD
