Metadata-Version: 2.1
Name: confyml
Version: 2.1.5
Summary: Small package to apply YAML config to methods and functions
Home-page: https://github.com/iccyp/confyml
Author: iccyp
Author-email: iccyp.py@gmail.com
License: UNKNOWN
Download-URL: https://github.com/iccyp/confyml/archive/2.1.5.tar.gz
Platform: UNKNOWN
Classifier: Programming Language :: Python :: 3
Classifier: License :: OSI Approved :: MIT License
Classifier: Operating System :: OS Independent
Requires-Python: >=3.6
Requires-Dist: PyYAML
